{
  "project_info": {
    "project_number": "1063972067161",
    "project_id": "poke-proyecto",
    "storage_bucket": "poke-proyecto.firebasestorage.app"
  },
  "client": [
    {
      "client_info": {
        "mobilesdk_app_id": "1:1063972067161:android:babfc56fe3ec7270629e48",
        "android_client_info": {
          "package_name": "com.example.practica11"
        }
      },
      "oauth_client": [],
      "api_key": [
        {
          "current_key": "AIzaSyC2Ue8RuFkkPtligbuVRMtrHzFy2351xH8"
        }
      ],
      "services": {
        "appinvite_service": {
          "other_platform_oauth_client": []
        }
      }
    }
  ],
  "configuration_version": "1"
}